omx_sdk/__init__.py
omx_sdk-0.2.1.dist-info/METADATA
omx_sdk-0.2.1.dist-info/WHEEL
omx_sdk-0.2.1.dist-info/licenses/LICENSE
omx_sdk-0.2.1.dist-info/RECORD
