Metadata-Version: 2.4
Name: omx-sdk
Version: 0.2.1
Summary: Official Python SDK for Oxinion Marketing Exchange - Multi-channel marketing automation with push notifications, email, geotriggers, beacons, and webhooks
Project-URL: Homepage, https://github.com/oxinion/omx-sdk
Project-URL: Repository, https://github.com/oxinion/omx-sdk.git
Project-URL: Documentation, https://github.com/oxinion/omx-sdk#readme
Project-URL: Bug Tracker, https://github.com/oxinion/omx-sdk/issues
Author-email: Oxinion <support@oxinion.com>
License: MIT License
License-File: LICENSE
Keywords: automation,beacon,campaign,email,exchange,geofencing,geotrigger,location-based,marketing,omx,oxinion,proximity-marketing,push-notification,sdk,webhook
Classifier: Development Status :: 4 - Beta
Classifier: Intended Audience :: Developers
Classifier: License :: OSI Approved :: MIT License
Classifier: Programming Language :: Python :: 3
Classifier: Programming Language :: Python :: 3.9
Classifier: Programming Language :: Python :: 3.10
Classifier: Programming Language :: Python :: 3.11
Classifier: Programming Language :: Python :: 3.12
Classifier: Topic :: Software Development :: Libraries :: Python Modules
Requires-Python: >=3.9
Requires-Dist: httpx>=0.25.0
Provides-Extra: dev
Requires-Dist: black; extra == 'dev'
Requires-Dist: mypy; extra == 'dev'
Requires-Dist: openapi-python-client; extra == 'dev'
Requires-Dist: pytest-asyncio; extra == 'dev'
Requires-Dist: pytest-cov; extra == 'dev'
Requires-Dist: pytest>=7.0; extra == 'dev'
Requires-Dist: ruff; extra == 'dev'
Provides-Extra: docs
Requires-Dist: sphinx; extra == 'docs'
Requires-Dist: sphinx-rtd-theme; extra == 'docs'
